README.md
setup.py
inscode_api/__init__.py
inscode_api/send_question.py
inscode_api.egg-info/PKG-INFO
inscode_api.egg-info/SOURCES.txt
inscode_api.egg-info/dependency_links.txt
inscode_api.egg-info/requires.txt
inscode_api.egg-info/top_level.txt