Metadata-Version: 2.1
Name: inscode-api
Version: 0.4
Summary: A library for interacting with the INSCODE API
Home-page: UNKNOWN
Author: yanhui
Author-email: yanhui@csdn.net
License: MIT
Platform: UNKNOWN
